setup.py
lesspy/__init__.py
lesspy.egg-info/PKG-INFO
lesspy.egg-info/SOURCES.txt
lesspy.egg-info/dependency_links.txt
lesspy.egg-info/not-zip-safe
lesspy.egg-info/top_level.txt
lesspy/tests/__init__.py