Metadata-Version: 1.0
Name: lesspy
Version: 0.1
Summary: 
